LICENSE
MANIFEST.in
README.rst
setup.cfg
setup.py
django_duat.egg-info/PKG-INFO
django_duat.egg-info/SOURCES.txt
django_duat.egg-info/dependency_links.txt
django_duat.egg-info/top_level.txt
duat/__init__.py
duat/admin.py
duat/middleware.py
duat/models.py
duat/renderhtml.js
duat/settings.py
duat/urls.py
duat/views.py
duat/wsgi.py
duat/migrations/0001_initial.py
duat/migrations/__init__.py
duat/static/duat/css/admin.css
duat/static/duat/css/feedback.css
duat/static/duat/images/ajax-loader.gif
duat/templates/duat/admin.js
duat/templates/duat/feedback.js
duat/templates/duat/home.html