Metadata-Version: 1.1
Name: django-duat
Version: 1.0
Summary: A lightweight Django User Acceptance Testing feedback tool.
Home-page: https://github.com/chrispbailey/duat/
Author: Chris Bailey
Author-email: chris.p.bailey@gmail.com
License: MIT License
Platform: UNKNOWN
Classifier: Environment :: Web Environment
Classifier: Framework :: Django
Classifier: Intended Audience :: Developers
Classifier: License :: OSI Approved :: MIT License
Classifier: Operating System :: OS Independent
Classifier: Programming Language :: Python
Classifier: Topic :: Software Development :: Libraries :: Python Modules
Classifier: Topic :: Software Development :: Testing
Classifier: Topic :: Internet :: WWW/HTTP :: Dynamic Content
